MANIFEST.in
README.md
setup.py
gswrap/Gswrap.py
gswrap/__init__.py
gswrap.egg-info/PKG-INFO
gswrap.egg-info/SOURCES.txt
gswrap.egg-info/dependency_links.txt
gswrap.egg-info/not-zip-safe
gswrap.egg-info/requires.txt
gswrap.egg-info/top_level.txt