Metadata-Version: 1.0
Name: gswrap
Version: 0.0.2
Summary: gswrap is wrapper libs for Google Sheet Rest API.
Home-page: https://github.com/nabeen/gswrap
Author: nabeen
Author-email: watanabe_kenichiro@hasigo.co.jp
License: UNKNOWN
Platform: UNKNOWN
